anime_renamer/__init__.py
anime_renamer/__main__.py
anime_renamer/downloader.py
anime_renamer/main.py
anime_renamer/organiser.py
anime_renamer/prepare.py
anime_renamer/remover.py
anime_renamer/renamer.py
anime_renamer/rollback.py
anime_renamer-0.5.dist-info/DESCRIPTION.rst
anime_renamer-0.5.dist-info/METADATA
anime_renamer-0.5.dist-info/RECORD
anime_renamer-0.5.dist-info/WHEEL
anime_renamer-0.5.dist-info/entry_points.txt
anime_renamer-0.5.dist-info/metadata.json
anime_renamer-0.5.dist-info/top_level.txt
