Metadata-Version: 2.0
Name: anime-renamer
Version: 0.5
Summary: UNKNOWN
Home-page: https://github.com/smsriharsha/anime-renamer
Author: kudoark
Author-email: UNKNOWN
License: MIT
Platform: UNKNOWN
Classifier: Development Status :: 5 - Production/Stable
Classifier: Intended Audience :: Developers
Classifier: Operating System :: OS Independent
Classifier: Programming Language :: Python :: 2.7
Classifier: Programming Language :: Python :: 3.3
Classifier: Programming Language :: Python :: 3.4
Classifier: Programming Language :: Python :: 3.5
Classifier: Programming Language :: Python :: 3.6
Classifier: Topic :: Utilities
Requires-Dist: requests
Requires-Dist: tvdbsimple
